setup.py
telegram_qq_bot.egg-info/PKG-INFO
telegram_qq_bot.egg-info/SOURCES.txt
telegram_qq_bot.egg-info/dependency_links.txt
telegram_qq_bot.egg-info/requires.txt
telegram_qq_bot.egg-info/top_level.txt
telegramqqbot/telegramqqbot.py